peat.py
setup.py
peat.egg-info/PKG-INFO
peat.egg-info/SOURCES.txt
peat.egg-info/dependency_links.txt
peat.egg-info/entry_points.txt
peat.egg-info/top_level.txt