Metadata-Version: 1.0
Name: peat
Version: 1.0.0
Summary: Repeat commands!
Home-page: https://github.com/bmcorser/peat
Author: @bmcorser
Author-email: bmcorser@gmail.com
License: UNKNOWN
Platform: UNKNOWN
